slagg/__init__.py
slagg/_version.py
slagg/decomp.py
slagg/driver.py
slagg/geometry.py
slagg/grid.py
slagg/utils.py
slagg/__pycache__/grid.cpython-310.pyc
tests/__init__.py
tests/test_full_decomp.py
tests/stl_files/C100_reduced.stl
tests/stl_files/C100exportFlipped.stl
tests/stl_files/Moon.stl
tests/stl_files/Torus.stl
tests/stl_files/Torus_reduced.stl
tests/stl_files/coupler.stl
tests/stl_files/coupler_reduced.stl
slagg-0.1.1.dist-info/LICENSE
slagg-0.1.1.dist-info/METADATA
slagg-0.1.1.dist-info/WHEEL
slagg-0.1.1.dist-info/top_level.txt
slagg-0.1.1.dist-info/RECORD
