Metadata-Version: 2.1
Name: slagg
Version: 0.1.1
Summary: A tool for generating optimized decompositions of gridded geometries for simulation
Home-page: https://github.com/JarrodLeddy/slagg
Author: Jarrod Leddy
Author-email: jleddy@txcorp.com
License: MIT
Project-URL: Source, https://github.com/JarrodLeddy/slagg
Project-URL: Tracker, https://github.com/JarrodLeddy/slagg/issues
Classifier: Programming Language :: Python :: 3
Classifier: License :: OSI Approved :: MIT License
Classifier: Operating System :: OS Independent
Requires-Python: >=3.6
License-File: LICENSE
Requires-Dist: numpy (>=1.8)
Requires-Dist: scipy (>=1.6.3)
Requires-Dist: matplotlib (>=3.4.2)
Requires-Dist: numpy-stl (>=3.0)
Requires-Dist: importlib-metadata ; python_version < "3.8"
Provides-Extra: docs
Requires-Dist: sphinx (>=4.0.2) ; extra == 'docs'
Requires-Dist: sphinx-rtd-theme ; extra == 'docs'
Provides-Extra: tests
Requires-Dist: pytest (>=3.3.0) ; extra == 'tests'
Requires-Dist: pytest-cov (>=3.0.0) ; extra == 'tests'
